transformer_cloner/__init__.py
transformer_cloner/clone_distiller.py
transformer_cloner/cloner.py
transformer_cloner/embedding_strategy.py
transformer_cloner/pruning_config.py
transformer_cloner/sentence_transformer_cloner.py
transformer_cloner/sentence_transformer_distiller.py
transformer_cloner/vocab_pruned_tokenizer.py
transformer_cloner-0.2.10.dist-info/METADATA
transformer_cloner-0.2.10.dist-info/WHEEL
transformer_cloner-0.2.10.dist-info/licenses/LICENSE
transformer_cloner-0.2.10.dist-info/RECORD
