Metadata-Version: 2.4
Name: transformer-cloner
Version: 0.2.10
Summary: Clone and prune transformer models with new tokenizers
Project-URL: Homepage, https://github.com/AliTava662/transformer-cloner
Project-URL: Documentation, https://github.com/AliTava662/transformer-cloner#readme
Project-URL: Repository, https://github.com/AliTavakolian/transformer-cloner
Project-URL: Issues, https://github.com/AliTavakolian/transformer-cloner/issues
Author-email: Ali Bayram <malibayram20@gmail.com>
License-Expression: MIT
License-File: LICENSE
Keywords: deep-learning,huggingface,llm,model-cloning,model-pruning,tokenizer,transformers
Classifier: Development Status :: 4 - Beta
Classifier: Intended Audience :: Developers
Classifier: Intended Audience :: Science/Research
Classifier: License :: OSI Approved :: MIT License
Classifier: Operating System :: OS Independent
Classifier: Programming Language :: Python :: 3
Classifier: Programming Language :: Python :: 3.10
Classifier: Programming Language :: Python :: 3.11
Classifier: Programming Language :: Python :: 3.12
Classifier: Topic :: Scientific/Engineering :: Artificial Intelligence
Requires-Python: >=3.10
Requires-Dist: datasets>=2.0.0
Requires-Dist: sentence-transformers>=2.0.0
Requires-Dist: torch>=2.0.0
Requires-Dist: tqdm>=4.0.0
Requires-Dist: transformers>=4.40.0
Provides-Extra: dev
Requires-Dist: build>=1.0.0; extra == 'dev'
Requires-Dist: pytest>=7.0.0; extra == 'dev'
Requires-Dist: twine>=4.0.0; extra == 'dev'
